setup.py
Products/__init__.py
Products.SimpleCalendarPortlet.egg-info/PKG-INFO
Products.SimpleCalendarPortlet.egg-info/SOURCES.txt
Products.SimpleCalendarPortlet.egg-info/dependency_links.txt
Products.SimpleCalendarPortlet.egg-info/entry_points.txt
Products.SimpleCalendarPortlet.egg-info/namespace_packages.txt
Products.SimpleCalendarPortlet.egg-info/not-zip-safe
Products.SimpleCalendarPortlet.egg-info/requires.txt
Products.SimpleCalendarPortlet.egg-info/top_level.txt
Products/SimpleCalendarPortlet/SimpleCalendar_calendar.pt
Products/SimpleCalendarPortlet/SimpleCalendar_calendar.pt.bak
Products/SimpleCalendarPortlet/__init__.py
Products/SimpleCalendarPortlet/calendar.py
Products/SimpleCalendarPortlet/changes.txt
Products/SimpleCalendarPortlet/configure.zcml
Products/SimpleCalendarPortlet/readme.txt
Products/SimpleCalendarPortlet/vocabularies.py
Products/SimpleCalendarPortlet/profiles/default/metadata.xml
Products/SimpleCalendarPortlet/profiles/default/portlets.xml
Products/SimpleCalendarPortlet/profiles/default/skins.xml